MANIFEST.in
README.txt
setup.cfg
setup.py
docs/Makefile
docs/epydoc.conf.cfg
docs/source/conf.py
docs/source/_static/pentacle_logo.png
pentacle/__init__.py
pentacle/application.py
pentacle/architecture.py
pentacle/config.py
pentacle/debugging.py
pentacle/encoding.py
pentacle/network.py
pentacle/packaging.py
pentacle/runtime.py
pentacle/security.py
pentacle/server.py
pentacle/storage.py
pentacle.egg-info/PKG-INFO
pentacle.egg-info/SOURCES.txt
pentacle.egg-info/dependency_links.txt
pentacle.egg-info/top_level.txt
pentacle/bus/__init__.py
pentacle/bus/services.py
pentacle/bus/spline.py
pentacle/bus/partners/__init__.py
pentacle/bus/partners/cluster.py
pentacle/bus/partners/main.py
pentacle/client/__init__.py
pentacle/client/cli.py
pentacle/client/support.py
pentacle/servicelib/__init__.py
pentacle/servicelib/cron.py
pentacle/servicelib/docmgr.py
pentacle/servicelib/registry.py
pentacle/servicelib/web/__init__.py
pentacle/servicelib/web/falcon/__init__.py
pentacle/servicelib/web/falcon/manage.py
pentacle/servicelib/web/falcon/settings.py
pentacle/servicelib/web/falcon/urls.py
pentacle/servicelib/web/falcon/views.py
pentacle/servicelib/web/falcon/media/css/status.css
pentacle/servicelib/web/falcon/media/images/action.png
pentacle/servicelib/web/falcon/media/images/favicon.ico
pentacle/servicelib/web/falcon/media/images/pentacle_bg.png
pentacle/servicelib/web/falcon/media/images/point.png
pentacle/servicelib/web/falcon/media/js/status.js
pentacle/servicelib/web/falcon/templates/page_base.html
pentacle/servicelib/web/falcon/templates/status.html
scripts/notemgr.py
scripts/registry-connect
scripts/registry-shutdown
scripts/registry.env
scripts/run-registry.sh
scripts/spline-shutdown
scripts/spline.cfg
scripts/spline.sh
scripts/user-login
scripts/partners/projects-repos.ptr
scripts/partners/registry.ptr
scripts/partners/skype-terminal.ptr
scripts/partners/stuphmud-autorun.ptr
scripts/partners/stuphmud.ptr
scripts/partners/web-facing.ptr
scripts/partners/westmetal.ptr