Metadata-Version: 1.0
Name: pentacle
Version: 0.4
Summary: An O-O P2P RPC protocol and application framework.
Home-page: http://www.penobscotrobotics.us/cms/page/pentacle
Author: Clint Banis
Author-email: cbanis@gmail.com
License: PSF
Download-URL: http://frauncache.googlecode.com/svn/trunk/Pentacle
Keywords: python.objects.remote,spline,pentacle,wsgi,web,rpc,p2p,remote
Platform: OS-independent
Platform: Many
Classifier: Development Status :: 2 - Pre-Alpha
Classifier: License :: OSI Approved :: Python Software Foundation License
Classifier: Programming Language :: Python :: 2
Classifier: Operating System :: OS Independent
Classifier: Environment :: Console
Classifier: Environment :: Web Environment
Classifier: Environment :: Plugins
Classifier: Framework :: Django
Classifier: Topic :: Scientific/Engineering
Classifier: Topic :: Software Development :: Libraries :: Python Modules
Classifier: Topic :: Software Development :: Embedded Systems
Classifier: Topic :: Software Development :: Libraries :: Application Frameworks
Classifier: Topic :: Internet :: WWW/HTTP :: WSGI :: Application
Classifier: Topic :: Internet :: WWW/HTTP :: WSGI :: Middleware
Classifier: Topic :: Internet :: WWW/HTTP :: WSGI :: Server
Classifier: Topic :: Internet :: WWW/HTTP :: HTTP Servers
Classifier: Topic :: Internet :: Proxy Servers
Classifier: Topic :: System :: Networking
Classifier: Topic :: System :: Clustering
Classifier: Topic :: System :: Distributed Computing
Classifier: Topic :: System :: Systems Administration
Classifier: Topic :: Office/Business :: Groupware
Classifier: Topic :: Office/Business :: Scheduling
Classifier: Topic :: Utilities
Classifier: Intended Audience :: System Administrators
Classifier: Intended Audience :: End Users/Desktop
Classifier: Intended Audience :: Science/Research
Classifier: Intended Audience :: Education
